gocept.country-3.0-py3.11-nspkg.pth
gocept/country/README.txt
gocept/country/__init__.py
gocept/country/configure.zcml
gocept/country/db.py
gocept/country/ftesting.zcml
gocept/country/interfaces.py
gocept/country/sources.py
gocept/country/tests/test_db.py
gocept/country/tests/test_doctest.py
gocept.country-3.0.dist-info/LICENSE.txt
gocept.country-3.0.dist-info/METADATA
gocept.country-3.0.dist-info/WHEEL
gocept.country-3.0.dist-info/namespace_packages.txt
gocept.country-3.0.dist-info/top_level.txt
gocept.country-3.0.dist-info/RECORD
