Metadata-Version: 2.1
Name: gocept.country
Version: 3.0
Summary: Zope 3 sources for pycountry databases
Home-page: https://github.com/gocept/gocept.country
Author: gocept gmbh & co. kg
Author-email: mail@gocept.com
License: ZPL 2.1
Keywords: country subdivision language currency iso 3166 639 4217 15924 3166-2 zope pycountry
Classifier: Development Status :: 5 - Production/Stable
Classifier: Environment :: Web Environment
Classifier: Intended Audience :: Developers
Classifier: License :: OSI Approved
Classifier: License :: OSI Approved :: Zope Public License
Classifier: Programming Language :: Python
Classifier: Programming Language :: Python :: 3
Classifier: Programming Language :: Python :: 3.7
Classifier: Programming Language :: Python :: 3.8
Classifier: Programming Language :: Python :: 3.9
Classifier: Programming Language :: Python :: 3.10
Classifier: Programming Language :: Python :: 3.11
Classifier: Programming Language :: Python :: Implementation :: CPython
Classifier: Programming Language :: Python :: Implementation :: PyPy
Classifier: Natural Language :: English
Classifier: Operating System :: OS Independent
Classifier: Topic :: Internet :: WWW/HTTP
Requires-Python: >=3.7
License-File: LICENSE.txt
Requires-Dist: setuptools
Requires-Dist: pycountry (>=16.0)
Requires-Dist: zope.i18nmessageid
Requires-Dist: zc.sourcefactory (>=0.3.3)
Requires-Dist: zope.deferredimport
Provides-Extra: test
Requires-Dist: zope.testing ; extra == 'test'
Requires-Dist: zope.app.wsgi[testlayer] ; extra == 'test'
Requires-Dist: zope.security ; extra == 'test'
Requires-Dist: zope.schema ; extra == 'test'
